alas_webapp/__init__.py
alas_webapp/__version__.py
alas_webapp/app.asar
alas_webapp-0.3.7.0.dist-info/LICENSE
alas_webapp-0.3.7.0.dist-info/METADATA
alas_webapp-0.3.7.0.dist-info/WHEEL
alas_webapp-0.3.7.0.dist-info/top_level.txt
alas_webapp-0.3.7.0.dist-info/RECORD
